desk/__init__.py
desk/console_commands.py
desk/main.py
desk/fitting/__init__.py
desk/fitting/dusty_fit.py
desk/fitting/fitting_tools.py
desk/fitting/tests/test_fitting_tools.py
desk/models/amorphous-carbon_models.hdf5
desk/models/amorphous-carbon_outputs.hdf5
desk/models/silicates_models.hdf5
desk/models/silicates_outputs.hdf5
desk/outputs/__init__.py
desk/outputs/interpolate_dusty.py
desk/outputs/parameter_ranges.py
desk/outputs/plot_pdf.py
desk/outputs/plotting_seds.py
desk/put_target_data_here/IRAS_04407-7000.csv
desk/put_target_data_here/IRAS_04509-6922.csv
desk/put_target_data_here/MSX_LMC_807.csv
desk/set_up/__init__.py
desk/set_up/config.py
desk/set_up/create_output_files.py
desk/set_up/error_messages.py
desk/set_up/full_grid.py
desk/set_up/get_data.py
desk/set_up/get_inputs.py
desk/set_up/get_models.py
desk/set_up/scale_dusty.py
desk/set_up/scale_external.py
desk/set_up/vizier_sed.py
desk/set_up/tests/test_full_grid.py
desk/set_up/tests/test_scale_dusty.py
desk/tests/test_console_commands.py
desk/tests/baseline_images/output_sed_sample_target_1.png
desk/tests/baseline_images/output_sed_sample_target_2.png
desk/tests/baseline_images/output_sed_sample_target_3.png
desk/tests/baseline_images/test_single_sed.png
desk-1.9.0.dist-info/LICENSE
desk-1.9.0.dist-info/METADATA
desk-1.9.0.dist-info/WHEEL
desk-1.9.0.dist-info/entry_points.txt
desk-1.9.0.dist-info/top_level.txt
desk-1.9.0.dist-info/RECORD
