Metadata-Version: 2.2
Name: desk
Version: 1.9.0
Summary: The DESK is an SED-fitting python scripts for fitting data from evolved stars
Home-page: https://github.com/s-goldman/Dusty-Evolved-Star-Kit/
Author: Steven R. Goldman
Author-email: sgoldman@stsci.edu
License: BSD license
Keywords: Dusty-Evolved-Star-Kit
Classifier: Development Status :: 2 - Pre-Alpha
Classifier: Intended Audience :: Developers
Classifier: License :: OSI Approved :: BSD License
Classifier: Natural Language :: English
Classifier: Programming Language :: Python :: 3.10
Classifier: Programming Language :: Python :: 3.11
Classifier: Programming Language :: Python :: 3.12
License-File: LICENSE
Requires-Dist: astropy
Requires-Dist: numpy
Requires-Dist: scipy
Requires-Dist: tqdm
Requires-Dist: ipdb
Requires-Dist: matplotlib
Requires-Dist: h5py
Requires-Dist: wheel
Requires-Dist: twine
Requires-Dist: sphinx
Requires-Dist: sphinx_automodapi
Requires-Dist: pytest-cov
Dynamic: author
Dynamic: author-email
Dynamic: classifier
Dynamic: description
Dynamic: home-page
Dynamic: keywords
Dynamic: license
Dynamic: requires-dist
Dynamic: summary
